termighty/__init__.py
termighty/config.ini
termighty/data/keymaps.json
termighty/data/rgb.json
termighty/data/styles.json
termighty/obj/__init__.py
termighty/obj/color.py
termighty/obj/string.py
termighty/settings/__init__.py
termighty/settings/config.py
termighty/settings/data.py
termighty/settings/system.py
termighty/utils/__init__.py
termighty/utils/key_processor.py
termighty/utils/listener.py
termighty/utils/term.py
termighty/widgets/__init__.py
termighty/widgets/text_box.py
termighty/widgets/text_editor.py
Termighty-3.0.5.dist-info/LICENSE
Termighty-3.0.5.dist-info/METADATA
Termighty-3.0.5.dist-info/WHEEL
Termighty-3.0.5.dist-info/top_level.txt
Termighty-3.0.5.dist-info/RECORD
